pbsq/__init__.py
pbsq/console/__init__.py
pbsq/server/__init__.py
pbsq-0.1.1.dist-info/LICENSE
pbsq-0.1.1.dist-info/METADATA
pbsq-0.1.1.dist-info/WHEEL
pbsq-0.1.1.dist-info/entry_points.txt
pbsq-0.1.1.dist-info/RECORD
